python_calamine-0.5.4.dist-info/METADATA
python_calamine-0.5.4.dist-info/WHEEL
python_calamine-0.5.4.dist-info/licenses/LICENSE
python_calamine.libs/libgcc_s-98a1ef30.so.1
python_calamine/__init__.py
python_calamine/_python_calamine.cpython-314t-x86_64-linux-musl.so
python_calamine/_python_calamine.pyi
python_calamine/py.typed
python_calamine-0.5.4.dist-info/RECORD
