Metadata-Version: 2.4
Name: python-calamine
Version: 0.5.4
Classifier: Development Status :: 4 - Beta
Classifier: Programming Language :: Rust
Classifier: Programming Language :: Python :: 3.10
Classifier: Programming Language :: Python :: 3.11
Classifier: Programming Language :: Python :: 3.12
Classifier: Programming Language :: Python :: 3.13
Classifier: Programming Language :: Python :: 3.14
License-File: LICENSE
Summary: Python binding for Rust's library for reading excel and odf file - calamine
Author-email: Dmitriy <dimastbk@proton.me>
License-Expression: MIT
Requires-Python: >=3.10
Project-URL: homepage, https://github.com/dimastbk/python-calamine
Project-URL: source, https://github.com/dimastbk/python-calamine
